Metadata-Version: 1.0
Name: cmdline-csv2shp
Version: 0.1.0
Summary: Python command line application for converting csv to shapefile.
Home-page: https://hrwallingford.com
Author: Abdulvahab Kharadi
Author-email: a.kharadi@hrwallingford.com
License: UNKNOWN
Platform: UNKNOWN
